simpledev/__init__.py
simpledev/ftext.py
simpledev/timer.py
simpledev-0.0.0.post2.dist-info/METADATA
simpledev-0.0.0.post2.dist-info/WHEEL
simpledev-0.0.0.post2.dist-info/top_level.txt
simpledev-0.0.0.post2.dist-info/RECORD
