Metadata-Version: 2.4
Name: simpledev
Version: 0.0.0.post2
Home-page: 
Author: Scholoch
Author-email: alf.201105@gmail.com
Keywords: easy develop debug simpledev development debugging dev simple edad
Classifier: Programming Language :: Python :: 3.13
Classifier: License :: OSI Approved :: MIT License
Classifier: Operating System :: OS Independent
Requires-Python: >=3.6
Dynamic: author
Dynamic: author-email
Dynamic: classifier
Dynamic: description
Dynamic: description-content-type
Dynamic: keywords
Dynamic: requires-python
